<?xml version="1.0" encoding="utf-8"?>
<mst_mapenemy2_data xmlns:i="http://www.w3.org/2001/XMLSchema-instance">
<mst_mapenemy2>
	<Id>1360101</Id>
	<Maparea_id>13</Maparea_id>
	<Mapinfo_no>6</Mapinfo_no>
	<Enemy_list_id>13601</Enemy_list_id>
	<Boss>0</Boss>
	<Deck_id>1</Deck_id>
	<Deck_name>敵偵察艦</Deck_name>
	<Formation_id>1</Formation_id>
	<E1_id>576</E1_id>
	<E1_lv>1</E1_lv>
	<E2_id>575</E2_id>
	<E2_lv>1</E2_lv>
	<E3_id>575</E3_id>
	<E3_lv>1</E3_lv>
	<E4_id>0</E4_id>
	<E4_lv>0</E4_lv>
	<E5_id>0</E5_id>
	<E5_lv>0</E5_lv>
	<E6_id>0</E6_id>
	<E6_lv>0</E6_lv>
	<Geth>20</Geth>
	<Experience>50</Experience>
</mst_mapenemy2>
<mst_mapenemy2>
	<Id>1360102</Id>
	<Maparea_id>13</Maparea_id>
	<Mapinfo_no>6</Mapinfo_no>
	<Enemy_list_id>13601</Enemy_list_id>
	<Boss>0</Boss>
	<Deck_id>2</Deck_id>
	<Deck_name>敵偵察艦</Deck_name>
	<Formation_id>1</Formation_id>
	<E1_id>575</E1_id>
	<E1_lv>1</E1_lv>
	<E2_id>502</E2_id>
	<E2_lv>1</E2_lv>
	<E3_id>502</E3_id>
	<E3_lv>1</E3_lv>
	<E4_id>0</E4_id>
	<E4_lv>0</E4_lv>
	<E5_id>0</E5_id>
	<E5_lv>0</E5_lv>
	<E6_id>0</E6_id>
	<E6_lv>0</E6_lv>
	<Geth>20</Geth>
	<Experience>40</Experience>
</mst_mapenemy2>
<mst_mapenemy2>
	<Id>1360103</Id>
	<Maparea_id>13</Maparea_id>
	<Mapinfo_no>6</Mapinfo_no>
	<Enemy_list_id>13601</Enemy_list_id>
	<Boss>0</Boss>
	<Deck_id>3</Deck_id>
	<Deck_name>敵偵察艦</Deck_name>
	<Formation_id>1</Formation_id>
	<E1_id>575</E1_id>
	<E1_lv>1</E1_lv>
	<E2_id>501</E2_id>
	<E2_lv>1</E2_lv>
	<E3_id>501</E3_id>
	<E3_lv>1</E3_lv>
	<E4_id>0</E4_id>
	<E4_lv>0</E4_lv>
	<E5_id>0</E5_id>
	<E5_lv>0</E5_lv>
	<E6_id>0</E6_id>
	<E6_lv>0</E6_lv>
	<Geth>20</Geth>
	<Experience>40</Experience>
</mst_mapenemy2>
<mst_mapenemy2>
	<Id>1360104</Id>
	<Maparea_id>13</Maparea_id>
	<Mapinfo_no>6</Mapinfo_no>
	<Enemy_list_id>13601</Enemy_list_id>
	<Boss>0</Boss>
	<Deck_id>4</Deck_id>
	<Deck_name>敵偵察艦</Deck_name>
	<Formation_id>1</Formation_id>
	<E1_id>503</E1_id>
	<E1_lv>1</E1_lv>
	<E2_id>502</E2_id>
	<E2_lv>1</E2_lv>
	<E3_id>501</E3_id>
	<E3_lv>1</E3_lv>
	<E4_id>0</E4_id>
	<E4_lv>0</E4_lv>
	<E5_id>0</E5_id>
	<E5_lv>0</E5_lv>
	<E6_id>0</E6_id>
	<E6_lv>0</E6_lv>
	<Geth>20</Geth>
	<Experience>35</Experience>
</mst_mapenemy2>
<mst_mapenemy2>
	<Id>1360105</Id>
	<Maparea_id>13</Maparea_id>
	<Mapinfo_no>6</Mapinfo_no>
	<Enemy_list_id>13601</Enemy_list_id>
	<Boss>0</Boss>
	<Deck_id>5</Deck_id>
	<Deck_name>敵偵察艦</Deck_name>
	<Formation_id>1</Formation_id>
	<E1_id>502</E1_id>
	<E1_lv>1</E1_lv>
	<E2_id>501</E2_id>
	<E2_lv>1</E2_lv>
	<E3_id>501</E3_id>
	<E3_lv>1</E3_lv>
	<E4_id>0</E4_id>
	<E4_lv>0</E4_lv>
	<E5_id>0</E5_id>
	<E5_lv>0</E5_lv>
	<E6_id>0</E6_id>
	<E6_lv>0</E6_lv>
	<Geth>20</Geth>
	<Experience>35</Experience>
</mst_mapenemy2>
<mst_mapenemy2>
	<Id>1360106</Id>
	<Maparea_id>13</Maparea_id>
	<Mapinfo_no>6</Mapinfo_no>
	<Enemy_list_id>13601</Enemy_list_id>
	<Boss>0</Boss>
	<Deck_id>6</Deck_id>
	<Deck_name>敵偵察艦</Deck_name>
	<Formation_id>1</Formation_id>
	<E1_id>501</E1_id>
	<E1_lv>1</E1_lv>
	<E2_id>501</E2_id>
	<E2_lv>1</E2_lv>
	<E3_id>0</E3_id>
	<E3_lv>0</E3_lv>
	<E4_id>0</E4_id>
	<E4_lv>0</E4_lv>
	<E5_id>0</E5_id>
	<E5_lv>0</E5_lv>
	<E6_id>0</E6_id>
	<E6_lv>0</E6_lv>
	<Geth>20</Geth>
	<Experience>30</Experience>
</mst_mapenemy2>
<mst_mapenemy2>
	<Id>1360107</Id>
	<Maparea_id>13</Maparea_id>
	<Mapinfo_no>6</Mapinfo_no>
	<Enemy_list_id>13601</Enemy_list_id>
	<Boss>0</Boss>
	<Deck_id>7</Deck_id>
	<Deck_name>敵偵察艦</Deck_name>
	<Formation_id>1</Formation_id>
	<E1_id>503</E1_id>
	<E1_lv>1</E1_lv>
	<E2_id>0</E2_id>
	<E2_lv>0</E2_lv>
	<E3_id>0</E3_id>
	<E3_lv>0</E3_lv>
	<E4_id>0</E4_id>
	<E4_lv>0</E4_lv>
	<E5_id>0</E5_id>
	<E5_lv>0</E5_lv>
	<E6_id>0</E6_id>
	<E6_lv>0</E6_lv>
	<Geth>20</Geth>
	<Experience>40</Experience>
</mst_mapenemy2>
<mst_mapenemy2>
	<Id>1360108</Id>
	<Maparea_id>13</Maparea_id>
	<Mapinfo_no>6</Mapinfo_no>
	<Enemy_list_id>13601</Enemy_list_id>
	<Boss>0</Boss>
	<Deck_id>8</Deck_id>
	<Deck_name>敵偵察艦</Deck_name>
	<Formation_id>1</Formation_id>
	<E1_id>502</E1_id>
	<E1_lv>1</E1_lv>
	<E2_id>0</E2_id>
	<E2_lv>0</E2_lv>
	<E3_id>0</E3_id>
	<E3_lv>0</E3_lv>
	<E4_id>0</E4_id>
	<E4_lv>0</E4_lv>
	<E5_id>0</E5_id>
	<E5_lv>0</E5_lv>
	<E6_id>0</E6_id>
	<E6_lv>0</E6_lv>
	<Geth>20</Geth>
	<Experience>35</Experience>
</mst_mapenemy2>
<mst_mapenemy2>
	<Id>1360109</Id>
	<Maparea_id>13</Maparea_id>
	<Mapinfo_no>6</Mapinfo_no>
	<Enemy_list_id>13601</Enemy_list_id>
	<Boss>0</Boss>
	<Deck_id>9</Deck_id>
	<Deck_name>敵偵察艦</Deck_name>
	<Formation_id>1</Formation_id>
	<E1_id>501</E1_id>
	<E1_lv>1</E1_lv>
	<E2_id>0</E2_id>
	<E2_lv>0</E2_lv>
	<E3_id>0</E3_id>
	<E3_lv>0</E3_lv>
	<E4_id>0</E4_id>
	<E4_lv>0</E4_lv>
	<E5_id>0</E5_id>
	<E5_lv>0</E5_lv>
	<E6_id>0</E6_id>
	<E6_lv>0</E6_lv>
	<Geth>20</Geth>
	<Experience>30</Experience>
</mst_mapenemy2>
<mst_mapenemy2>
	<Id>1360201</Id>
	<Maparea_id>13</Maparea_id>
	<Mapinfo_no>6</Mapinfo_no>
	<Enemy_list_id>13602</Enemy_list_id>
	<Boss>0</Boss>
	<Deck_id>1</Deck_id>
	<Deck_name>敵はぐれ艦隊</Deck_name>
	<Formation_id>1</Formation_id>
	<E1_id>576</E1_id>
	<E1_lv>1</E1_lv>
	<E2_id>576</E2_id>
	<E2_lv>1</E2_lv>
	<E3_id>575</E3_id>
	<E3_lv>1</E3_lv>
	<E4_id>575</E4_id>
	<E4_lv>1</E4_lv>
	<E5_id>0</E5_id>
	<E5_lv>0</E5_lv>
	<E6_id>0</E6_id>
	<E6_lv>0</E6_lv>
	<Geth>0</Geth>
	<Experience>50</Experience>
</mst_mapenemy2>
<mst_mapenemy2>
	<Id>1360202</Id>
	<Maparea_id>13</Maparea_id>
	<Mapinfo_no>6</Mapinfo_no>
	<Enemy_list_id>13602</Enemy_list_id>
	<Boss>0</Boss>
	<Deck_id>2</Deck_id>
	<Deck_name>敵はぐれ艦隊</Deck_name>
	<Formation_id>1</Formation_id>
	<E1_id>575</E1_id>
	<E1_lv>1</E1_lv>
	<E2_id>575</E2_id>
	<E2_lv>1</E2_lv>
	<E3_id>501</E3_id>
	<E3_lv>1</E3_lv>
	<E4_id>501</E4_id>
	<E4_lv>1</E4_lv>
	<E5_id>0</E5_id>
	<E5_lv>0</E5_lv>
	<E6_id>0</E6_id>
	<E6_lv>0</E6_lv>
	<Geth>0</Geth>
	<Experience>45</Experience>
</mst_mapenemy2>
<mst_mapenemy2>
	<Id>1360203</Id>
	<Maparea_id>13</Maparea_id>
	<Mapinfo_no>6</Mapinfo_no>
	<Enemy_list_id>13602</Enemy_list_id>
	<Boss>0</Boss>
	<Deck_id>3</Deck_id>
	<Deck_name>敵はぐれ艦隊</Deck_name>
	<Formation_id>1</Formation_id>
	<E1_id>575</E1_id>
	<E1_lv>1</E1_lv>
	<E2_id>501</E2_id>
	<E2_lv>1</E2_lv>
	<E3_id>501</E3_id>
	<E3_lv>1</E3_lv>
	<E4_id>501</E4_id>
	<E4_lv>1</E4_lv>
	<E5_id>0</E5_id>
	<E5_lv>0</E5_lv>
	<E6_id>0</E6_id>
	<E6_lv>0</E6_lv>
	<Geth>0</Geth>
	<Experience>40</Experience>
</mst_mapenemy2>
<mst_mapenemy2>
	<Id>1360204</Id>
	<Maparea_id>13</Maparea_id>
	<Mapinfo_no>6</Mapinfo_no>
	<Enemy_list_id>13602</Enemy_list_id>
	<Boss>0</Boss>
	<Deck_id>4</Deck_id>
	<Deck_name>敵はぐれ艦隊</Deck_name>
	<Formation_id>1</Formation_id>
	<E1_id>503</E1_id>
	<E1_lv>1</E1_lv>
	<E2_id>502</E2_id>
	<E2_lv>1</E2_lv>
	<E3_id>501</E3_id>
	<E3_lv>1</E3_lv>
	<E4_id>501</E4_id>
	<E4_lv>1</E4_lv>
	<E5_id>0</E5_id>
	<E5_lv>0</E5_lv>
	<E6_id>0</E6_id>
	<E6_lv>0</E6_lv>
	<Geth>0</Geth>
	<Experience>35</Experience>
</mst_mapenemy2>
<mst_mapenemy2>
	<Id>1360205</Id>
	<Maparea_id>13</Maparea_id>
	<Mapinfo_no>6</Mapinfo_no>
	<Enemy_list_id>13602</Enemy_list_id>
	<Boss>0</Boss>
	<Deck_id>5</Deck_id>
	<Deck_name>敵はぐれ艦隊</Deck_name>
	<Formation_id>1</Formation_id>
	<E1_id>503</E1_id>
	<E1_lv>1</E1_lv>
	<E2_id>501</E2_id>
	<E2_lv>1</E2_lv>
	<E3_id>501</E3_id>
	<E3_lv>1</E3_lv>
	<E4_id>0</E4_id>
	<E4_lv>0</E4_lv>
	<E5_id>0</E5_id>
	<E5_lv>0</E5_lv>
	<E6_id>0</E6_id>
	<E6_lv>0</E6_lv>
	<Geth>0</Geth>
	<Experience>35</Experience>
</mst_mapenemy2>
<mst_mapenemy2>
	<Id>1360206</Id>
	<Maparea_id>13</Maparea_id>
	<Mapinfo_no>6</Mapinfo_no>
	<Enemy_list_id>13602</Enemy_list_id>
	<Boss>0</Boss>
	<Deck_id>6</Deck_id>
	<Deck_name>敵はぐれ艦隊</Deck_name>
	<Formation_id>1</Formation_id>
	<E1_id>503</E1_id>
	<E1_lv>1</E1_lv>
	<E2_id>502</E2_id>
	<E2_lv>1</E2_lv>
	<E3_id>0</E3_id>
	<E3_lv>0</E3_lv>
	<E4_id>0</E4_id>
	<E4_lv>0</E4_lv>
	<E5_id>0</E5_id>
	<E5_lv>0</E5_lv>
	<E6_id>0</E6_id>
	<E6_lv>0</E6_lv>
	<Geth>0</Geth>
	<Experience>30</Experience>
</mst_mapenemy2>
<mst_mapenemy2>
	<Id>1360207</Id>
	<Maparea_id>13</Maparea_id>
	<Mapinfo_no>6</Mapinfo_no>
	<Enemy_list_id>13602</Enemy_list_id>
	<Boss>0</Boss>
	<Deck_id>7</Deck_id>
	<Deck_name>敵はぐれ艦隊</Deck_name>
	<Formation_id>1</Formation_id>
	<E1_id>502</E1_id>
	<E1_lv>1</E1_lv>
	<E2_id>502</E2_id>
	<E2_lv>1</E2_lv>
	<E3_id>0</E3_id>
	<E3_lv>0</E3_lv>
	<E4_id>0</E4_id>
	<E4_lv>0</E4_lv>
	<E5_id>0</E5_id>
	<E5_lv>0</E5_lv>
	<E6_id>0</E6_id>
	<E6_lv>0</E6_lv>
	<Geth>0</Geth>
	<Experience>30</Experience>
</mst_mapenemy2>
<mst_mapenemy2>
	<Id>1360208</Id>
	<Maparea_id>13</Maparea_id>
	<Mapinfo_no>6</Mapinfo_no>
	<Enemy_list_id>13602</Enemy_list_id>
	<Boss>0</Boss>
	<Deck_id>8</Deck_id>
	<Deck_name>敵はぐれ艦隊</Deck_name>
	<Formation_id>1</Formation_id>
	<E1_id>502</E1_id>
	<E1_lv>1</E1_lv>
	<E2_id>501</E2_id>
	<E2_lv>1</E2_lv>
	<E3_id>0</E3_id>
	<E3_lv>0</E3_lv>
	<E4_id>0</E4_id>
	<E4_lv>0</E4_lv>
	<E5_id>0</E5_id>
	<E5_lv>0</E5_lv>
	<E6_id>0</E6_id>
	<E6_lv>0</E6_lv>
	<Geth>0</Geth>
	<Experience>30</Experience>
</mst_mapenemy2>
<mst_mapenemy2>
	<Id>1360209</Id>
	<Maparea_id>13</Maparea_id>
	<Mapinfo_no>6</Mapinfo_no>
	<Enemy_list_id>13602</Enemy_list_id>
	<Boss>0</Boss>
	<Deck_id>9</Deck_id>
	<Deck_name>敵はぐれ艦隊</Deck_name>
	<Formation_id>1</Formation_id>
	<E1_id>501</E1_id>
	<E1_lv>1</E1_lv>
	<E2_id>501</E2_id>
	<E2_lv>1</E2_lv>
	<E3_id>0</E3_id>
	<E3_lv>0</E3_lv>
	<E4_id>0</E4_id>
	<E4_lv>0</E4_lv>
	<E5_id>0</E5_id>
	<E5_lv>0</E5_lv>
	<E6_id>0</E6_id>
	<E6_lv>0</E6_lv>
	<Geth>0</Geth>
	<Experience>30</Experience>
</mst_mapenemy2>
<mst_mapenemy2>
	<Id>1360301</Id>
	<Maparea_id>13</Maparea_id>
	<Mapinfo_no>6</Mapinfo_no>
	<Enemy_list_id>13603</Enemy_list_id>
	<Boss>1</Boss>
	<Deck_id>1</Deck_id>
	<Deck_name>敵主力艦隊</Deck_name>
	<Formation_id>1</Formation_id>
	<E1_id>554</E1_id>
	<E1_lv>1</E1_lv>
	<E2_id>575</E2_id>
	<E2_lv>1</E2_lv>
	<E3_id>575</E3_id>
	<E3_lv>1</E3_lv>
	<E4_id>575</E4_id>
	<E4_lv>1</E4_lv>
	<E5_id>575</E5_id>
	<E5_lv>1</E5_lv>
	<E6_id>0</E6_id>
	<E6_lv>0</E6_lv>
	<Geth>0</Geth>
	<Experience>60</Experience>
</mst_mapenemy2>
<mst_mapenemy2>
	<Id>1360302</Id>
	<Maparea_id>13</Maparea_id>
	<Mapinfo_no>6</Mapinfo_no>
	<Enemy_list_id>13603</Enemy_list_id>
	<Boss>1</Boss>
	<Deck_id>2</Deck_id>
	<Deck_name>敵主力艦隊</Deck_name>
	<Formation_id>1</Formation_id>
	<E1_id>554</E1_id>
	<E1_lv>1</E1_lv>
	<E2_id>575</E2_id>
	<E2_lv>1</E2_lv>
	<E3_id>575</E3_id>
	<E3_lv>1</E3_lv>
	<E4_id>502</E4_id>
	<E4_lv>1</E4_lv>
	<E5_id>502</E5_id>
	<E5_lv>1</E5_lv>
	<E6_id>0</E6_id>
	<E6_lv>0</E6_lv>
	<Geth>0</Geth>
	<Experience>60</Experience>
</mst_mapenemy2>
<mst_mapenemy2>
	<Id>1360303</Id>
	<Maparea_id>13</Maparea_id>
	<Mapinfo_no>6</Mapinfo_no>
	<Enemy_list_id>13603</Enemy_list_id>
	<Boss>1</Boss>
	<Deck_id>3</Deck_id>
	<Deck_name>敵主力艦隊</Deck_name>
	<Formation_id>1</Formation_id>
	<E1_id>554</E1_id>
	<E1_lv>1</E1_lv>
	<E2_id>575</E2_id>
	<E2_lv>1</E2_lv>
	<E3_id>503</E3_id>
	<E3_lv>1</E3_lv>
	<E4_id>502</E4_id>
	<E4_lv>1</E4_lv>
	<E5_id>502</E5_id>
	<E5_lv>1</E5_lv>
	<E6_id>0</E6_id>
	<E6_lv>0</E6_lv>
	<Geth>1</Geth>
	<Experience>55</Experience>
</mst_mapenemy2>
<mst_mapenemy2>
	<Id>1360304</Id>
	<Maparea_id>13</Maparea_id>
	<Mapinfo_no>6</Mapinfo_no>
	<Enemy_list_id>13603</Enemy_list_id>
	<Boss>1</Boss>
	<Deck_id>4</Deck_id>
	<Deck_name>敵主力艦隊</Deck_name>
	<Formation_id>1</Formation_id>
	<E1_id>554</E1_id>
	<E1_lv>1</E1_lv>
	<E2_id>575</E2_id>
	<E2_lv>1</E2_lv>
	<E3_id>502</E3_id>
	<E3_lv>1</E3_lv>
	<E4_id>502</E4_id>
	<E4_lv>1</E4_lv>
	<E5_id>0</E5_id>
	<E5_lv>0</E5_lv>
	<E6_id>0</E6_id>
	<E6_lv>0</E6_lv>
	<Geth>1</Geth>
	<Experience>55</Experience>
</mst_mapenemy2>
<mst_mapenemy2>
	<Id>1360305</Id>
	<Maparea_id>13</Maparea_id>
	<Mapinfo_no>6</Mapinfo_no>
	<Enemy_list_id>13603</Enemy_list_id>
	<Boss>1</Boss>
	<Deck_id>5</Deck_id>
	<Deck_name>敵主力艦隊</Deck_name>
	<Formation_id>1</Formation_id>
	<E1_id>554</E1_id>
	<E1_lv>1</E1_lv>
	<E2_id>503</E2_id>
	<E2_lv>1</E2_lv>
	<E3_id>502</E3_id>
	<E3_lv>1</E3_lv>
	<E4_id>502</E4_id>
	<E4_lv>1</E4_lv>
	<E5_id>0</E5_id>
	<E5_lv>0</E5_lv>
	<E6_id>0</E6_id>
	<E6_lv>0</E6_lv>
	<Geth>1</Geth>
	<Experience>55</Experience>
</mst_mapenemy2>
<mst_mapenemy2>
	<Id>1360306</Id>
	<Maparea_id>13</Maparea_id>
	<Mapinfo_no>6</Mapinfo_no>
	<Enemy_list_id>13603</Enemy_list_id>
	<Boss>1</Boss>
	<Deck_id>6</Deck_id>
	<Deck_name>敵主力艦隊</Deck_name>
	<Formation_id>1</Formation_id>
	<E1_id>518</E1_id>
	<E1_lv>1</E1_lv>
	<E2_id>503</E2_id>
	<E2_lv>1</E2_lv>
	<E3_id>502</E3_id>
	<E3_lv>1</E3_lv>
	<E4_id>502</E4_id>
	<E4_lv>1</E4_lv>
	<E5_id>0</E5_id>
	<E5_lv>0</E5_lv>
	<E6_id>0</E6_id>
	<E6_lv>0</E6_lv>
	<Geth>2</Geth>
	<Experience>55</Experience>
</mst_mapenemy2>
<mst_mapenemy2>
	<Id>1360307</Id>
	<Maparea_id>13</Maparea_id>
	<Mapinfo_no>6</Mapinfo_no>
	<Enemy_list_id>13603</Enemy_list_id>
	<Boss>1</Boss>
	<Deck_id>7</Deck_id>
	<Deck_name>敵主力艦隊</Deck_name>
	<Formation_id>1</Formation_id>
	<E1_id>505</E1_id>
	<E1_lv>1</E1_lv>
	<E2_id>503</E2_id>
	<E2_lv>1</E2_lv>
	<E3_id>502</E3_id>
	<E3_lv>1</E3_lv>
	<E4_id>502</E4_id>
	<E4_lv>1</E4_lv>
	<E5_id>0</E5_id>
	<E5_lv>0</E5_lv>
	<E6_id>0</E6_id>
	<E6_lv>0</E6_lv>
	<Geth>2</Geth>
	<Experience>50</Experience>
</mst_mapenemy2>
<mst_mapenemy2>
	<Id>1360308</Id>
	<Maparea_id>13</Maparea_id>
	<Mapinfo_no>6</Mapinfo_no>
	<Enemy_list_id>13603</Enemy_list_id>
	<Boss>1</Boss>
	<Deck_id>8</Deck_id>
	<Deck_name>敵主力艦隊</Deck_name>
	<Formation_id>1</Formation_id>
	<E1_id>505</E1_id>
	<E1_lv>1</E1_lv>
	<E2_id>502</E2_id>
	<E2_lv>1</E2_lv>
	<E3_id>502</E3_id>
	<E3_lv>1</E3_lv>
	<E4_id>0</E4_id>
	<E4_lv>0</E4_lv>
	<E5_id>0</E5_id>
	<E5_lv>0</E5_lv>
	<E6_id>0</E6_id>
	<E6_lv>0</E6_lv>
	<Geth>2</Geth>
	<Experience>50</Experience>
</mst_mapenemy2>
<mst_mapenemy2>
	<Id>1360309</Id>
	<Maparea_id>13</Maparea_id>
	<Mapinfo_no>6</Mapinfo_no>
	<Enemy_list_id>13603</Enemy_list_id>
	<Boss>1</Boss>
	<Deck_id>9</Deck_id>
	<Deck_name>敵主力艦隊</Deck_name>
	<Formation_id>1</Formation_id>
	<E1_id>505</E1_id>
	<E1_lv>1</E1_lv>
	<E2_id>501</E2_id>
	<E2_lv>1</E2_lv>
	<E3_id>501</E3_id>
	<E3_lv>1</E3_lv>
	<E4_id>0</E4_id>
	<E4_lv>0</E4_lv>
	<E5_id>0</E5_id>
	<E5_lv>0</E5_lv>
	<E6_id>0</E6_id>
	<E6_lv>0</E6_lv>
	<Geth>2</Geth>
	<Experience>50</Experience>
</mst_mapenemy2>
</mst_mapenemy2_data>
